Workbook

Sheet Resumen
A1: RAPHAEL EVENTOS — Modelo de costos multi-tenant
A2: Costos reales de infraestructura (SaaS multi-tenant en la nube) + modelo de precios Básica/Pro. Fuentes y fecha de consulta en la pestaña 'Fuentes'.
A4: Supuestos ajustables
A5: Cambiá los valores en azul/amarillo — el resto del archivo se recalcula solo.
A7: Parámetro | B7: Valor | C7: Unidad | D7: Nota
A8: Escenario A — cantidad de salones (piloto) | B8: 1 | C8: salones | D8: Raphael Eventos solo, ahora mismo
A9: Escenario B — cantidad de salones (crecimiento) | B9: 15 | C9: salones | D9: primeros clientes fuera de Raphael
A10: Escenario C — cantidad de salones (grupo completo) | B10: 60 | C10: salones | D10: el grupo de salones de Fede
A11: Tamaño de base de datos por salón | B11: 100 | C11: MB | D11: eventos, clientes, invitados, costeo
A12: Almacenamiento por salón (contratos, QR, adjuntos) | B12: 1 | C12: GB | D12: las fotos del evento son un link externo, no ocupan espacio propio
A13: Usuarios activos mensuales (MAU) por salón | B13: 150 | C13: usuarios | D13: titulares + invitados que abren la app en el mes
A14: Mensajes de WhatsApp (recordatorios) por salón/mes | B14: 30 | C14: mensajes | D14: Fase 2 — recordatorios automáticos de vencimiento
A15: Precio WhatsApp utility en Argentina | B15: 0.012 | C15: USD/mensaje | D15: tarifa de referencia, a confirmar en Meta Business Manager
A16: Conversaciones de servicio gratis por mes | B16: 1000 | C16: conversaciones | D16: asumido compartido entre todos los tenants (1 cuenta de Meta)
A17: Emails transaccionales por salón/mes | B17: 200 | C17: emails | D17: confirmaciones, recupero de contraseña, etc.
A18: Costo de dominio | B18: 15 | C18: USD/año | D18: un dominio .com o .app
A19: Edge requests por salón/mes (Vercel) | B19: 0.5 | C19: millones | D19: estimado para un salón de actividad media
... A25: Fee de alta Pro (única vez) | B25: 600 | C25: USD | D25: incluye configurar la importación del Excel de costeo
A27: Todas las celdas en azul sobre fondo amarillo son supuestos editables. El resto de las pestañas las referencian con fórmulas.

Sheet Infraestructura
A1: Costo mensual de infraestructura, por escenario de escala
A2: Escenario A = piloto (Raphael Eventos solo) · B = 15 salones · C = los 60 salones del grupo de Fede. Precios reales de cada proveedor, ver pestaña 'Fuentes'.
A4: Servicio | B4: Qué incluye / free tier | C4: Escenario A (1) | D4: Escenario B (15) | E4: Escenario C (60) | F4: Nota
A5: Vercel (hosting + PWA) | B5: Plan Pro obligatorio (Hobby no permite uso comercial): US$20 base, incluye 10M edge requests y 1TB de transferencia; excedente US$2/1M requests y US$0.15/GB | C5: =20 + MAX(0,Resumen!$B$8*Resumen!$B$19-10)*2 + MAX(0,Resumen!$B$8*Resumen!$B$20-1000)*0.15 -> 20 | D5: =20 + MAX(0,Resumen!$B$9*Resumen!$B$19-10)*2 + MAX(0,Resumen!$B$9*Resumen!$B$20-1000)*0.15 -> 20 | E5: =20 + MAX(0,Resumen!$B$10*Resumen!$B$19-10)*2 + MAX(0,Resumen!$B$10*Resumen!$B$20-1000)*0.15 -> 90
A6: Supabase (base de datos + auth + storage) | B6: Free hasta 500MB BD / 1GB storage / 50k MAU; Pro US$25 con 8GB BD, 100GB storage y 100k MAU incluidos, luego overage por GB/MAU | C6: =IF(AND((Resumen!$B$8*Resumen!$B$11/1024)<=0.5,(Resumen!$B$8*Resumen!$B$12)<=1,(Resumen!$B$8*Resumen!$B$13)<=50000),0,25+MAX(0,(Resumen!$B$8*Resumen!$B$11/1024)-8)*0.125+MAX(0,(Resumen!$B$8*Resumen!$B$12)-100)*0.0213+MAX(0,(Resumen!$B$8*Resumen!$B$13)-100000)*0.00325) -> 0 | D6: =IF(AND((Resumen!$B$9*Resumen!$B$11/1024)<=0.5,(Resumen!$B$9*Resumen!$B$12)<=1,(Resumen!$B$9*Resumen!$B$13)<=50000),0,25+MAX(0,(Resumen!$B$9*Resumen!$B$11/1024)-8)*0.125+MAX(0,(Resumen!$B$9*Resumen!$B$12)-100)*0.0213+MAX(0,(Resumen!$B$9*Resumen!$B$13)-100000)*0.00325) -> 25 | E6: =IF(AND((Resumen!$B$10*Resumen!$B$11/1024)<=0.5,(Resumen!$B$10*Resumen!$B$12)<=1,(Resumen!$B$10*Resumen!$B$13)<=50000),0,25+MAX(0,(Resumen!$B$10*Resumen!$B$11/1024)-8)*0.125+MAX(0,(Resumen!$B$10*Resumen!$B$12)-100)*0.0213+MAX(0,(Resumen!$B$10*Resumen!$B$13)-100000)*0.00325) -> 25
A7: WhatsApp Business API (Fase 2, recordatorios) | B7: Meta cobra por conversación de 24hs; ~1000 conversaciones de servicio gratis por cuenta; tarifa utility Argentina ~US$0.012 | C7: =MAX(0,Resumen!$B$8*Resumen!$B$14-Resumen!$B$16)*Resumen!$B$15 -> 0 | D7: =MAX(0,Resumen!$B$9*Resumen!$B$14-Resumen!$B$16)*Resumen!$B$15 -> 0 | E7: =MAX(0,Resumen!$B$10*Resumen!$B$14-Resumen!$B$16)*Resumen!$B$15 -> 9.6
A8: Resend (emails transaccionales) | B8: Free hasta 3.000 emails/mes; Pro US$20 hasta 50.000 emails, luego US$0.90 cada 1.000 | C8: =IF((Resumen!$B$8*Resumen!$B$17)<=3000,0,IF((Resumen!$B$8*Resumen!$B$17)<=50000,20,20+((Resumen!$B$8*Resumen!$B$17)-50000)/1000*0.9)) -> 0 | D8: =IF((Resumen!$B$9*Resumen!$B$17)<=3000,0,IF((Resumen!$B$9*Resumen!$B$17)<=50000,20,20+((Resumen!$B$9*Resumen!$B$17)-50000)/1000*0.9)) -> 0 | E8: =IF((Resumen!$B$10*Resumen!$B$17)<=3000,0,IF((Resumen!$B$10*Resumen!$B$17)<=50000,20,20+((Resumen!$B$10*Resumen!$B$17)-50000)/1000*0.9)) -> 20
A9: Dominio + SSL | B9: SSL gratis (Vercel/Cloudflare); dominio .com/.app ~US$15/año | C9: =Resumen!$B$18/12 -> 1.25 | D9: =Resumen!$B$18/12 -> 1.25 | E9: =Resumen!$B$18/12 -> 1.25
A10: Total mensual de infraestructura | C10: =SUM(C5:C9) -> 21.25 | D10: =SUM(D5:D9) -> 46.25 | E10: =SUM(E5:E9) -> 145.85
A11: Costo de infraestructura por salón / mes | C11: =C10/Resumen!$B$8 -> 21.25 | D11: =D10/Resumen!$B$9 -> 3.0833333 | E11: =E10/Resumen!$B$10 -> 2.4308333
A13: El costo de WhatsApp asume una sola cuenta de Meta Business compartida por la plataforma (las 1.000 conversaciones gratis se reparten entre todos los salones, no son 1.000 por salón). Validar con una prueba piloto antes de comprometerse a un número exacto.

Sheet Planes y precios
A1: Planes: Básica y Pro
A2: Básica: lo que usa el salón día a día. Pro: suma el módulo de costeo/stock — pensado para el dueño, no para el cliente final.
A4: Funcionalidad | B4: Básica | C4: Pro
A5: Landing comercial + cotización | B5: ✓ | C5: ✓
A6: Portal cliente: eventos, saldo, tarjetas por tipo | B6: ✓ | C6: ✓
A7: Actualización automática por IPC | B7: ✓ | C7: ✓
A8: Multi-evento por cliente (mismo login) | B8: ✓ | C8: ✓
A9: Calendario de disponibilidad del salón | B9: ✓ | C9: ✓
A10: CRM de consultas / vendedor | B10: ✓ | C10: ✓
A11: Rol invitado: confirmar asistencia + QR de ingreso | B11: ✓ | C11: ✓
A12: Directorio de proveedores aliados | B12: ✓ | C12: ✓
A13: Reportes de ocupación y ventas | B13: ✓ | C13: ✓
A14: Módulo de costeo por evento (importación de Excel) | B14: — | C14: ✓
A15: Reportes de margen / costo real por evento | B15: — | C15: ✓
A16: Estructura de costeo configurable (multi-salón) | B16: — | C16: ✓
A18: Precio propuesto
A19: Mensual, por salón | B19: =Resumen!$B$22 -> 29 | C19: =Resumen!$B$23 -> 69
A20: Alta / onboarding (única vez) | B20: =Resumen!$B$24 -> 300 | C20: =Resumen!$B$25 -> 600
A22: Margen vs. costo de infraestructura
A23: (tomando el costo por salón del Escenario B — 15 salones — de la pestaña Infraestructura)
A24: Costo de infraestructura / salón / mes | B24: =Infraestructura!$D$11 -> 3.0833333 | C24: =Infraestructura!$D$11 -> 3.0833333
A25: Margen bruto mensual, por salón | B25: =B19-B24 -> 25.916667 | C25: =C19-C24 -> 65.916667
A26: Margen bruto, % | B26: =B25/B19 -> 0.89367816 | C26: =C25/C19 -> 0.95531401
A28: El margen no incluye el tiempo de soporte/mantenimiento de Hernán ni comisiones de venta — solo el costo puro de infraestructura. Los precios de esta pestaña están en la pestaña Resumen: cambialos ahí.

Sheet Proyección de ingresos
A1: Proyección: ingresos vs. costo de infraestructura
A2: La columna 'Salones' es editable (azul) — probá otros escenarios de adopción. El resto se recalcula solo.
A4: Salones activos | B4: Ingreso mensual | C4: Costo infraestructura | D4: Margen bruto | E4: Margen % | F4: Nota
A5: 1 | B5: =A5*(Resumen!$B$21*Resumen!$B$23+(1-Resumen!$B$21)*Resumen!$B$22) -> 41 | C5: =(20+MAX(0,A5*Resumen!$B$19-10)*2+MAX(0,A5*Resumen!$B$20-1000)*0.15)+(IF(AND((A5*Resumen!$B$11/1024)<=0.5,(A5*Resumen!$B$12)<=1,(A5*Resumen!$B$13)<=50000),0,25+MAX(0,(A5*Resumen!$B$11/1024)-8)*0.125+MAX(0,(A5*Resumen!$B$12)-100)*0.0213+MAX(0,(A5*Resumen!$B$13)-100000)*0.00325))+(MAX(0,A5*Resumen!$B$14-Resumen!$B$16)*Resumen!$B$15)+(IF((A5*Resumen!$B$17)<=3000,0,IF((A5*Resumen!$B$17)<=50000,20,20+((A5*Resumen!$B$17)-50000)/1000*0.9)))+(Resumen!$B$18/12) -> 21.25 | D5: =B5-C5 -> 19.75 | E5: =IF(B5=0,0,D5/B5) -> 0.48170732 | F5: Raphael Eventos solo (piloto actual)
A6: 5 | B6: =A6*(Resumen!$B$21*Resumen!$B$23+(1-Resumen!$B$21)*Resumen!$B$22) -> 205 | C6: =(20+MAX(0,A6*Resumen!$B$19-10)*2+MAX(0,A6*Resumen!$B$20-1000)*0.15)+(IF(AND((A6*Resumen!$B$11/1024)<=0.5,(A6*Resumen!$B$12)<=1,(A6*Resumen!$B$13)<=50000),0,25+MAX(0,(A6*Resumen!$B$11/1024)-8)*0.125+MAX(0,(A6*Resumen!$B$12)-100)*0.0213+MAX(0,(A6*Resumen!$B$13)-100000)*0.00325))+(MAX(0,A6*Resumen!$B$14-Resumen!$B$16)*Resumen!$B$15)+(IF((A6*Resumen!$B$17)<=3000,0,IF((A6*Resumen!$B$17)<=50000,20,20+((A6*Resumen!$B$17)-50000)/1000*0.9)))+(Resumen!$B$18/12) -> 46.25 | D6: =B6-C6 -> 158.75 | E6: =IF(B6=0,0,D6/B6) -> 0.77439024
A7: 10 | B7: =A7*(Resumen!$B$21*Resumen!$B$23+(1-Resumen!$B$21)*Resumen!$B$22) -> 410 | C7: =(20+MAX(0,A7*Resumen!$B$19-10)*2+MAX(0,A7*Resumen!$B$20-1000)*0.15)+(IF(AND((A7*Resumen!$B$11/1024)<=0.5,(A7*Resumen!$B$12)<=1,(A7*Resumen!$B$13)<=50000),0,25+MAX(0,(A7*Resumen!$B$11/1024)-8)*0.125+MAX(0,(A7*Resumen!$B$12)-100)*0.0213+MAX(0,(A7*Resumen!$B$13)-100000)*0.00325))+(MAX(0,A7*Resumen!$B$14-Resumen!$B$16)*Resumen!$B$15)+(IF((A7*Resumen!$B$17)<=3000,0,IF((A7*Resumen!$B$17)<=50000,20,20+((A7*Resumen!$B$17)-50000)/1000*0.9)))+(Resumen!$B$18/12) -> 46.25 | D7: =B7-C7 -> 363.75 | E7: =IF(B7=0,0,D7/B7) -> 0.88719512
A8: 15 | B8: =A8*(Resumen!$B$21*Resumen!$B$23+(1-Resumen!$B$21)*Resumen!$B$22) -> 615 | C8: =(20+MAX(0,A8*Resumen!$B$19-10)*2+MAX(0,A8*Resumen!$B$20-1000)*0.15)+(IF(AND((A8*Resumen!$B$11/1024)<=0.5,(A8*Resumen!$B$12)<=1,(A8*Resumen!$B$13)<=50000),0,25+MAX(0,(A8*Resumen!$B$11/1024)-8)*0.125+MAX(0,(A8*Resumen!$B$12)-100)*0.0213+MAX(0,(A8*Resumen!$B$13)-100000)*0.00325))+(MAX(0,A8*Resumen!$B$14-Resumen!$B$16)*Resumen!$B$15)+(IF((A8*Resumen!$B$17)<=3000,0,IF((A8*Resumen!$B$17)<=50000,20,20+((A8*Resumen!$B$17)-50000)/1000*0.9)))+(Resumen!$B$18/12) -> 46.25 | D8: =B8-C8 -> 568.75 | E8: =IF(B8=0,0,D8/B8) -> 0.92479675 | F8: Escenario B de la pestaña Infraestructura
A9: 25 | B9: =A9*(Resumen!$B$21*Resumen!$B$23+(1-Resumen!$B$21)*Resumen!$B$22) -> 1025 | C9: =(20+MAX(0,A9*Resumen!$B$19-10)*2+MAX(0,A9*Resumen!$B$20-1000)*0.15)+(IF(AND((A9*Resumen!$B$11/1024)<=0.5,(A9*Resumen!$B$12)<=1,(A9*Resumen!$B$13)<=50000),0,25+MAX(0,(A9*Resumen!$B$11/1024)-8)*0.125+MAX(0,(A9*Resumen!$B$12)-100)*0.0213+MAX(0,(A9*Resumen!$B$13)-100000)*0.00325))+(MAX(0,A9*Resumen!$B$14-Resumen!$B$16)*Resumen!$B$15)+(IF((A9*Resumen!$B$17)<=3000,0,IF((A9*Resumen!$B$17)<=50000,20,20+((A9*Resumen!$B$17)-50000)/1000*0.9)))+(Resumen!$B$18/12) -> 71.25 | D9: =B9-C9 -> 953.75 | E9: =IF(B9=0,0,D9/B9) -> 0.9304878
A10: 40 | B10: =A10*(Resumen!$B$21*Resumen!$B$23+(1-Resumen!$B$21)*Resumen!$B$22) -> 1640 | C10: =(20+MAX(0,A10*Resumen!$B$19-10)*2+MAX(0,A10*Resumen!$B$20-1000)*0.15)+(IF(AND((A10*Resumen!$B$11/1024)<=0.5,(A10*Resumen!$B$12)<=1,(A10*Resumen!$B$13)<=50000),0,25+MAX(0,(A10*Resumen!$B$11/1024)-8)*0.125+MAX(0,(A10*Resumen!$B$12)-100)*0.0213+MAX(0,(A10*Resumen!$B$13)-100000)*0.00325))+(MAX(0,A10*Resumen!$B$14-Resumen!$B$16)*Resumen!$B$15)+(IF((A10*Resumen!$B$17)<=3000,0,IF((A10*Resumen!$B$17)<=50000,20,20+((A10*Resumen!$B$17)-50000)/1000*0.9)))+(Resumen!$B$18/12) -> 88.65 | D10: =B10-C10 -> 1551.35 | E10: =IF(B10=0,0,D10/B10) -> 0.94594512
A11: 60 | B11: =A11*(Resumen!$B$21*Resumen!$B$23+(1-Resumen!$B$21)*Resumen!$B$22) -> 2460 | C11: =(20+MAX(0,A11*Resumen!$B$19-10)*2+MAX(0,A11*Resumen!$B$20-1000)*0.15)+(IF(AND((A11*Resumen!$B$11/1024)<=0.5,(A11*Resumen!$B$12)<=1,(A11*Resumen!$B$13)<=50000),0,25+MAX(0,(A11*Resumen!$B$11/1024)-8)*0.125+MAX(0,(A11*Resumen!$B$12)-100)*0.0213+MAX(0,(A11*Resumen!$B$13)-100000)*0.00325))+(MAX(0,A11*Resumen!$B$14-Resumen!$B$16)*Resumen!$B$15)+(IF((A11*Resumen!$B$17)<=3000,0,IF((A11*Resumen!$B$17)<=50000,20,20+((A11*Resumen!$B$17)-50000)/1000*0.9)))+(Resumen!$B$18/12) -> 145.85 | D11: =B11-C11 -> 2314.15 | E11: =IF(B11=0,0,D11/B11) -> 0.94071138 | F11: el grupo completo de salones de Fede
A13: Ingreso = salones × precio mensual mezclado según el % de adopción del plan Pro (celda ajustable en Resumen). No incluye los fees de alta (única vez) ni el tiempo de soporte — son ingresos/costos recurrentes puros.

Sheet Fuentes
A1: Fuentes de los precios usados
A3: Servicio | B3: Fuente | C3: Consultado | D3: Nota
A4: Vercel | B4: https://vercel.com/pricing | C4: 19/08/2026 | D4: Plan Hobby prohíbe uso comercial — se asume Pro (US$20/mes) desde el día uno.
A5: Supabase | B5: https://supabase.com/pricing | C5: 19/08/2026 | D5: Free y Pro; overage por GB de BD/storage y por MAU.
A6: Cloudflare R2 | B6: https://developers.cloudflare.com/r2/pricing/ | C6: 19/08/2026 | D6: No se usa en el modelo base (Supabase Storage alcanza); queda como alternativa más barata si el storage crece mucho.
A7: WhatsApp Business API | B7: https://ominiflow.com/whatsapp-api-pricing/argentina | C7: 19/08/2026 | D7: Tarifas de Argentina de un agregador, no la tabla oficial de Meta (no se pudo acceder directamente) — validar en Meta Business Manager antes de cerrar precios con clientes.
A8: Resend | B8: https://resend.com/pricing | C8: 19/08/2026 | D8: Free y Pro; overage por cada 1.000 emails.
A10: Estos son precios de lista, en dólares, de agosto de 2026 — cambian con el tiempo y varían según impuestos locales, tipo de cambio y volumen real. Usar este archivo para dimensionar el negocio, no como cotización final: confirmar los números antes de firmar cualquier compromiso comercial.
